{
  "contract": "MBOmno",
  "operation": [
    {
      "service": "platform",
      "request": "configure",
      "parameter": {
        "version": 0,
        "incomeAccount": "8827069720377389395",
        "operationFee": {
          "chain": {
            "2": "0"
          }
        }
      }
    },
    {
      "service": "user",
      "request": "configure",
      "parameter": {
        "incomeAccount": "8827069720377389395",
        "contractPaysWithdrawFee": true,
        "withdrawMinimumNQT": {
          "chain": {
            "1": "100000000",
            "2": "100000000",
            "4": "100000000",
            "6": "100000"
          }
        },
        "withdrawTransactionFeeNQT": {
          "chain": {
            "1": "100000000",
            "2": "30000000",
            "4": "10000000",
            "6": "10000"
          }
        },
        "operationFee": {
          "chain": {
            "2": "0"
          }
        }
      }
    },
    {
      "service": "cardmorph",
      "request": "configure",
      "parameter": {
        "incomeAccount": "8827069720377389395",
        "operationFee": {
          "chain": {
            "2": "0"
          }
        },
        "contractPaysWithdrawFee": true,
        "definition": {
          "rank": [
            {
              "rank": 1,
              "chanceDuplicateIfNotMorphed": "1.0",
              "cost": {
                "asset": {
                  "10230963490193589789": "5000000000"
                }
              },
              "peer": {
                "asset": {
                  "65767141008711421": "1",
                  "3607141736374727634": "1",
                  "9451976923053037726": "1",
                  "10917692030112170713": "1",
                  "609721796834652174": "1",
                  "2795734210888256790": "1",
                  "13430257599807483745": "1",
                  "16326649816730553703": "1",
                  "10444425886085847503": "1",
                  "18101012326255288772": "1",
                  "8717959006135737805": "1",
                  "6086151229884242778": "1",
                  "8966516609271135665": "1",
                  "1941380340903453000": "1",
                  "5528548442683058721": "1",
                  "524790161704873898": "1",
                  "583958094572828441": "1",
                  "12313032092046113556": "1",
                  "4735490741705855799": "1",
                  "16412049206728355506": "1",
                  "9057629654312953814": "1",
                  "3865726407233803673": "1",
                  "374078224198142471": "1",
                  "7891814295348826088": "1",
                  "188493294393002400": "1",
                  "8825927167203958938": "1",
                  "7536385584787697086": "1",
                  "15284691712437925618": "1",
                  "488367278629756964": "1",
                  "1310229991284473521": "1",
                  "17472981396773816914": "1",
                  "1479526493428793943": "1",
                  "10229749181769297696": "1"
                }
              }
            },
            {
              "rank": 2,
              "chanceDuplicateIfNotMorphed": "0.3",
              "cost": {
                "asset": {
                  "10230963490193589789": "25000000000"
                }
              },
              "peer": {
                "asset": {
                  "1770779863759720918": "1",
                  "12936439663349626618": "1",
                  "7024690161218732154": "1",
                  "11654119158397769364": "1",
                  "6864800023593094679": "1",
                  "7535070915409870441": "1",
                  "16570943417360649598": "1",
                  "1462047204733593633": "1",
                  "13244842214545819858": "1",
                  "10956456574154580310": "1",
                  "5384772991499461482": "1"
                }
              }
            },
            {
              "rank": 3,
              "chanceDuplicateIfNotMorphed": "0.15",
              "cost": {
                "asset": {
                  "10230963490193589789": "75000000000"
                }
              },
              "peer": {
                "asset": {
                  "4367881087678870632": "1",
                  "15778342868690621160": "1",
                  "3758988694981372970": "1",
                  "1328293559375692481": "1",
                  "8026549983053279231": "1",
                  "9118586585609900793": "1"
                }
              }
            }
          ]
        }
      }
    }
  ]
}